{
  "UrlOPTarget": "https://gravitee/am/profnet/oidc/",
  "OPMetadata": "",
  "AccessToken1": "",
  "AccessToken2": "",
  "User1Name": "alice",
  "User2Name": "bob",
  "User1Pass": "W0nderland",
  "User2Pass": "Und3rland",
  "LoginScript": "var username = document.getElementById(\"username\");\nusername.value = \"§current_user_username§\";\n\nvar password = document.getElementById(\"password\");\npassword.value = \"§current_user_password§\";\n\nvar submitBtn = document.querySelector(\"div > button\");\nsubmitBtn.click();",
  "ConsentScript": "var authBtn = document.getElementsByName(\"user_oauth_approval\")[1]\nauthBtn.click();\n",
  "Client1Config": "",
  "Client2Config": ""
}
